marketfeed_multi_broker_sdk/__init__.py
marketfeed_multi_broker_sdk/broker_interface.py
marketfeed_multi_broker_sdk/broker_sdk.py
marketfeed_multi_broker_sdk/enums.py
marketfeed_multi_broker_sdk/models.py
marketfeed_multi_broker_sdk/brokers/__init__.py
marketfeed_multi_broker_sdk/brokers/fyers.py
marketfeed_multi_broker_sdk/brokers/iifl.py
marketfeed_multi_broker_sdk/brokers/kotak.py
marketfeed_multi_broker_sdk/brokers/kotak_neo.py
marketfeed_multi_broker_sdk/brokers/shoonya.py
marketfeed_multi_broker_sdk/brokers/xts.py
marketfeed_multi_broker_sdk/services/__init__.py
marketfeed_multi_broker_sdk/services/fyers_services.py
marketfeed_multi_broker_sdk/services/kotak_neo_services.py
marketfeed_multi_broker_sdk/services/kotak_services.py
marketfeed_multi_broker_sdk/services/shoonya_services.py
marketfeed_multi_broker_sdk/services/xts_services.py
marketfeed_multi_broker_sdk/utils/__init__.py
marketfeed_multi_broker_sdk/utils/env_generator.py
marketfeed_multi_broker_sdk/utils/jwt_handler.py
tests/__init__.py
tests/test_fyers.py
tests/test_fyers_mock.py
tests/test_kotak_neo.py
tests/test_shoonya.py
tests/test_xts.py
marketfeed_multi_broker_sdk-0.1.25.dist-info/METADATA
marketfeed_multi_broker_sdk-0.1.25.dist-info/WHEEL
marketfeed_multi_broker_sdk-0.1.25.dist-info/top_level.txt
marketfeed_multi_broker_sdk-0.1.25.dist-info/RECORD
