Metadata-Version: 2.1
Name: marketfeed-multi-broker-sdk
Version: 0.1.25
Summary: Multi Broker SDK
Home-page: https://github.com/tradeclone/multi-broker-sdk
Author: Faraz
Author-email: faraz.s@marketfeed.com
Requires-Dist: requests
Requires-Dist: pydantic
Requires-Dist: pyotp
Requires-Dist: load-dotenv
